neurokit2/__init__.py
neurokit2/benchmark/__init__.py
neurokit2/benchmark/benchmark_ecg.py
neurokit2/benchmark/benchmark_utils.py
neurokit2/bio/__init__.py
neurokit2/bio/bio_analyze.py
neurokit2/bio/bio_process.py
neurokit2/complexity/TODO_entropy_wiener.py
neurokit2/complexity/TODO_fractal_capacity.py
neurokit2/complexity/__init__.py
neurokit2/complexity/complexity.py
neurokit2/complexity/complexity_decorrelation.py
neurokit2/complexity/complexity_hjorth.py
neurokit2/complexity/complexity_lempelziv.py
neurokit2/complexity/complexity_lyapunov.py
neurokit2/complexity/complexity_relativeroughness.py
neurokit2/complexity/complexity_rqa.py
neurokit2/complexity/entropy_angular.py
neurokit2/complexity/entropy_approximate.py
neurokit2/complexity/entropy_attention.py
neurokit2/complexity/entropy_bubble.py
neurokit2/complexity/entropy_coalition.py
neurokit2/complexity/entropy_cosinesimilarity.py
neurokit2/complexity/entropy_cumulativeresidual.py
neurokit2/complexity/entropy_differential.py
neurokit2/complexity/entropy_dispersion.py
neurokit2/complexity/entropy_distribution.py
neurokit2/complexity/entropy_fuzzy.py
neurokit2/complexity/entropy_grid.py
neurokit2/complexity/entropy_hierarchical.py
neurokit2/complexity/entropy_increment.py
neurokit2/complexity/entropy_kl.py
neurokit2/complexity/entropy_kolmogorov.py
neurokit2/complexity/entropy_maximum.py
neurokit2/complexity/entropy_multiscale.py
neurokit2/complexity/entropy_ofentropy.py
neurokit2/complexity/entropy_permutation.py
neurokit2/complexity/entropy_phase.py
neurokit2/complexity/entropy_power.py
neurokit2/complexity/entropy_range.py
neurokit2/complexity/entropy_rate.py
neurokit2/complexity/entropy_renyi.py
neurokit2/complexity/entropy_sample.py
neurokit2/complexity/entropy_shannon.py
neurokit2/complexity/entropy_shannon_joint.py
neurokit2/complexity/entropy_slope.py
neurokit2/complexity/entropy_spectral.py
neurokit2/complexity/entropy_svd.py
neurokit2/complexity/entropy_symbolicdynamic.py
neurokit2cw-0.0.16.dist-info/AUTHORS.rst
neurokit2cw-0.0.16.dist-info/LICENSE
neurokit2cw-0.0.16.dist-info/METADATA
neurokit2cw-0.0.16.dist-info/WHEEL
neurokit2cw-0.0.16.dist-info/top_level.txt
neurokit2cw-0.0.16.dist-info/RECORD
