Metadata-Version: 2.1
Name: neurokit2cw
Version: 0.0.16
Summary: The Python Toolbox for Neurophysiological Signal Processing. Versão editada CardioWEB
Home-page: https://github.com/neuropsychology/NeuroKit
Author: Dominique Makowski
Author-email: dom.makowski@gmail.com
License: MIT license
Keywords: NeuroKit2,physiology,bodily signals,Python,ECG,EDA,EMG,PPG
Platform: UNKNOWN
Classifier: Development Status :: 2 - Pre-Alpha
Classifier: Intended Audience :: Developers
Classifier: License :: OSI Approved :: MIT License
Classifier: Natural Language :: English
Classifier: Programming Language :: Python :: 3.9
Classifier: Programming Language :: Python :: 3.10
Classifier: Programming Language :: Python :: 3.11
License-File: LICENSE
License-File: AUTHORS.rst
Requires-Dist: matplotlib
Requires-Dist: numpy
Requires-Dist: pandas
Requires-Dist: scikit-learn (>=1.0.0)
Requires-Dist: scipy
Provides-Extra: test
Requires-Dist: EMD-signal ; extra == 'test'
Requires-Dist: EntropyHub ; extra == 'test'
Requires-Dist: PyWavelets ; extra == 'test'
Requires-Dist: antropy ; extra == 'test'
Requires-Dist: astropy ; extra == 'test'
Requires-Dist: bioread ; extra == 'test'
Requires-Dist: biosppy (==0.6.1) ; extra == 'test'
Requires-Dist: coverage ; extra == 'test'
Requires-Dist: cvxopt ; extra == 'test'
Requires-Dist: matplotlib ; extra == 'test'
Requires-Dist: mne[data] ; extra == 'test'
Requires-Dist: nolds ; extra == 'test'
Requires-Dist: numpy ; extra == 'test'
Requires-Dist: pandas ; extra == 'test'
Requires-Dist: plotly ; extra == 'test'
Requires-Dist: pyentrp ; extra == 'test'
Requires-Dist: pytest ; extra == 'test'
Requires-Dist: scikit-learn (>=1.0.0) ; extra == 'test'
Requires-Dist: scipy ; extra == 'test'
Requires-Dist: ts2vg ; extra == 'test'
